hsettings/__init__.py
hsettings/hsettings.py
hsettings/loaders.py
hsettings-0.1.5.dist-info/METADATA
hsettings-0.1.5.dist-info/WHEEL
hsettings-0.1.5.dist-info/top_level.txt
hsettings-0.1.5.dist-info/RECORD
