Metadata-Version: 2.1
Name: hsettings
Version: 0.1.5
Summary: Python hybrid settings from multiple sources.
Home-page: https://github.com/wwtg99/hsettings
Author: wuwentao
Author-email: wwtg99@126.com
License: MIT
Keywords: settings
Platform: UNKNOWN
Classifier: Operating System :: OS Independent
Classifier: License :: OSI Approved :: MIT License
Classifier: Programming Language :: Python :: 3.5
Classifier: Programming Language :: Python :: 3.6
Classifier: Programming Language :: Python :: 3.7
Requires-Python: >=3.5
Requires-Dist: pyyaml (>=3.13)
